[
  {
    "id": 1,
    "quote": "Sire, Sire ! On en a gros !",
    "meta": "Perceval, Livre II, Les Exploit\u00e9s"
  },
  {
    "id": 2,
    "quote": "[Dame S\u00e9li : Les tartes, la p\u00eache, tout \u00e7a c'est du patrimoine] (Arthur, montrant la tarte) C'est du patrimoine \u00e7a ?",
    "meta": "Arthur, Livre I, La tarte aux myrtilles"
  },
  {
    "id": 3,
    "quote": "[\u00c0 Merlin] : Soit vous fabriquez s\u00e9ance tenante une potion de f\u00e9condit\u00e9 qui fonctionne mieux que vos flacons de pisse habituels, soit mon mari ici pr\u00e9sent se fera un plaisir d'outrepasser la hi\u00e9rarchie et de vous mettre une trempe maison!\n",
    "meta": "S\u00e9li, Livre III, 67 : La Potion de F\u00e9condit\u00e9 II"
  },
  {
    "id": 4,
    "quote": "Excusez ! Y a moyen de vous entretenir deux secondes ? [...] C'est au sujet que ce matin je suis pass\u00e9 devant vos enclos, et j'ai vu que vous aviez une jolie petite poule blanche ! [...] Une jolie petite poule vous voyez, le bel animal [...] \n",
    "meta": "Guethenoc, Livre III, 53 : Feue La Poule de Guethenoc"
  },
  {
    "id": 6,
    "quote": "2500 pi\u00e8ces d'or ???! Eh... eh... c'est un blague? 2500 pi\u00e8ces d'or, mais ou voulez vous que j'trouve 2500 pi\u00e8ces d'or, dans l'cul d'une vache ?!\n",
    "meta": "Seigneur Jacca, Livre I, 21 : La taxe militaire"
  },
  {
    "id": 7,
    "quote": "Progressif... N'oubliez pas, dans la casse, le plus important, c'est les suites d'\u00e9paisseurs ... B\u00fbche de 10, B\u00fbche de 16; B\u00fbche de 32, B\u00fbb\u00fbche, Bibuchette, et re B\u00fbche de 6 !!!\n",
    "meta": "Perceval, Livre V, Unagi V (ep.39)"
  },
  {
    "id": 8,
    "quote": "Une pluie de pierres en int\u00e9rieur donc ! Je vous prenais pour un pied de chaise mais vous \u00eates un pr\u00e9curseur en fait !\n",
    "meta": "\u00c9lias de Kelliwic'h, Livre IV, Le Privil\u00e9gi\u00e9"
  },
  {
    "id": 9,
    "quote": "Ca s'enferme les registres ! (Glaucia : Ah bon ? ) Ouais ! Et les trous du cul qui font pas leur boulot \u00e7a s'enferme aussi !\n",
    "meta": "Capito, Livre VI, 1 : Miles Ignotus"
  },
  {
    "id": 10,
    "quote": "Quoi, c'est parce que je pr\u00e9f\u00e8re les hommes c'est \u00e7a ? \u00c0 ce compte l\u00e0 faut virer Bohort aussi...\n",
    "meta": "Edern, \u00e9pisodes pilotes, 6 : Le Chevalier femme"
  },
  {
    "id": 11,
    "quote": "Dans le languedoc, ils m'appellent Provencal. Mais c'est moi qui m'suis gourr\u00e9 en disant mon nom. Sinon, en Bretagne, c'est le Gros Faisan au sud, et au nord, c'est juste Ducon ..\n",
    "meta": "Perceval, Livre III, Le Sanglier De Comouailles"
  },
  {
    "id": 12,
    "quote": "Et qu'est-ce qui font-ils, au gouvernement ? Y's'roucent les poules ! Y's'poulent les rouces ! (Guethenoc : Y's'roulent les pouces !) Voil\u00e0, mieux !\n",
    "meta": "Roparzh, Livre IV, 53 : Vox populi III"
  },
  {
    "id": "5bb5e68e8009d",
    "quote": "dd",
    "meta": "dd"
  }
]